Workbook

Sheet Transactions
A1: 💰 Personal Finance & Budget Tracker
A2: Date | B2: Description | C2: Category | D2: Type | E2: Amount (₹) | F2: Month
A3: 01/01/2025 | B3: Monthly Salary | C3: Salary | D3: Income | E3: 50000 | F3: January
A4: 03/01/2025 | B4: House Rent | C4: Rent | D4: Expense | E4: 12000 | F4: January
A5: 05/01/2025 | B5: Grocery Shopping | C5: Food | D5: Expense | E5: 3500 | F5: January
A6: 07/01/2025 | B6: Electricity Bill | C6: Utilities | D6: Expense | E6: 1200 | F6: January
A7: 10/01/2025 | B7: Mobile Recharge | C7: Utilities | D7: Expense | E7: 499 | F7: January
A8: 12/01/2025 | B8: Restaurant Dinner | C8: Food | D8: Expense | E8: 1800 | F8: January
A9: 15/01/2025 | B9: Freelance Payment | C9: Freelance | D9: Income | E9: 8000 | F9: January
A10: 18/01/2025 | B10: Bus & Auto Fare | C10: Transport | D10: Expense | E10: 900 | F10: January
A11: 20/01/2025 | B11: Movie & OTT | C11: Entertainment | D11: Expense | E11: 699 | F11: January
A12: 22/01/2025 | B12: Doctor Visit | C12: Healthcare | D12: Expense | E12: 500 | F12: January
A13: 25/01/2025 | B13: Grocery Shopping | C13: Food | D13: Expense | E13: 2800 | F13: January
A14: 28/01/2025 | B14: Internet Bill | C14: Utilities | D14: Expense | E14: 799 | F14: January
... A52: 28/04/2025 | B52: Shopping Clothes | C52: Entertainment | D52: Expense | E52: 2500 | F52: April

Sheet Summary Dashboard
B1: 📊 Personal Finance Summary Dashboard
B3: 💵 Total Income | D3: 💸 Total Expenses | F3: 💰 Net Savings | H3: 📈 Savings Rate
B4: =SUMIF(Transactions!D:D,"Income",Transactions!E:E) | D4: =SUMIF(Transactions!D:D,"Expense",Transactions!E:E) | F4: =B4-D4 | H4: =IF(B4>0,F4/B4,0)
B7: 📅 Monthly Breakdown
B8: Month | C8: Income (₹) | D8: Expenses (₹) | E8: Savings (₹) | F8: Savings %
B9: January | C9: =SUMIFS(Transactions!E:E,Transactions!F:F,"January",Transactions!D:D,"Income") | D9: =SUMIFS(Transactions!E:E,Transactions!F:F,"January",Transactions!D:D,"Expense") | E9: =C9-D9 | F9: =IF(C9>0,E9/C9,0)
B10: February | C10: =SUMIFS(Transactions!E:E,Transactions!F:F,"February",Transactions!D:D,"Income") | D10: =SUMIFS(Transactions!E:E,Transactions!F:F,"February",Transactions!D:D,"Expense") | E10: =C10-D10 | F10: =IF(C10>0,E10/C10,0)
B11: March | C11: =SUMIFS(Transactions!E:E,Transactions!F:F,"March",Transactions!D:D,"Income") | D11: =SUMIFS(Transactions!E:E,Transactions!F:F,"March",Transactions!D:D,"Expense") | E11: =C11-D11 | F11: =IF(C11>0,E11/C11,0)
B12: April | C12: =SUMIFS(Transactions!E:E,Transactions!F:F,"April",Transactions!D:D,"Income") | D12: =SUMIFS(Transactions!E:E,Transactions!F:F,"April",Transactions!D:D,"Expense") | E12: =C12-D12 | F12: =IF(C12>0,E12/C12,0)
B13: TOTAL | C13: =SUM(C9:C12) | D13: =SUM(D9:D12) | E13: =SUM(E9:E12) | F13: =IF(C13>0,E13/C13,0)
B15: 🏷️ Expense by Category
B16: Category | C16: Total Spent (₹) | D16: % of Expenses
B17: Food | C17: =SUMIFS(Transactions!E:E,Transactions!C:C,"Food",Transactions!D:D,"Expense") | D17: =IF(D4>0,C17/D4,0)
B18: Rent | C18: =SUMIFS(Transactions!E:E,Transactions!C:C,"Rent",Transactions!D:D,"Expense") | D18: =IF(D4>0,C18/D4,0)
B19: Utilities | C19: =SUMIFS(Transactions!E:E,Transactions!C:C,"Utilities",Transactions!D:D,"Expense") | D19: =IF(D4>0,C19/D4,0)
B20: Transport | C20: =SUMIFS(Transactions!E:E,Transactions!C:C,"Transport",Transactions!D:D,"Expense") | D20: =IF(D4>0,C20/D4,0)
B21: Entertainment | C21: =SUMIFS(Transactions!E:E,Transactions!C:C,"Entertainment",Transactions!D:D,"Expense") | D21: =IF(D4>0,C21/D4,0)
B22: Healthcare | C22: =SUMIFS(Transactions!E:E,Transactions!C:C,"Healthcare",Transactions!D:D,"Expense") | D22: =IF(D4>0,C22/D4,0)

Sheet Category Reference
A1: Category | B1: Type
A2: Salary | B2: Income
A3: Freelance | B3: Income
A4: Bonus | B4: Income
A5: Food | B5: Expense
A6: Rent | B6: Expense
A7: Utilities | B7: Expense
A8: Transport | B8: Expense
A9: Entertainment | B9: Expense
A10: Healthcare | B10: Expense
